<?xml version="1.0" encoding="utf-8"?>
<savedqueries xmlns:xsi="http://www.w3.org/2001/XMLSchema-instance">
  <savedquery>
    <IsCustomizable>1</IsCustomizable>
    <CanBeDeleted>0</CanBeDeleted>
    <isquickfindquery>0</isquickfindquery>
    <isprivate>0</isprivate>
    <isdefault>1</isdefault>
    <savedqueryid>{a2d21ff5-bddf-493d-a9ef-27e772a92563}</savedqueryid>
    <layoutxml>
      <grid name="cicd_housingunits" jump="cicd_unitname" select="1" icon="1" preview="1">
        <row name="cicd_housingunit" id="cicd_housingunitid">
          <cell name="cicd_unitname" width="300" />
          <cell name="createdon" width="125" />
        </row>
      </grid>
    </layoutxml>
    <querytype>2</querytype>
    <fetchxml>
      <fetch version="1.0" mapping="logical">
        <entity name="cicd_housingunit">
          <attribute name="cicd_housingunitid" />
          <attribute name="cicd_unitname" />
          <attribute name="createdon" />
          <order attribute="cicd_unitname" descending="false" />
          <filter type="and">
            <condition attribute="statecode" operator="eq" value="0" />
          </filter>
        </entity>
      </fetch>
    </fetchxml>
    <IntroducedVersion>1.0</IntroducedVersion>
    <LocalizedNames>
      <LocalizedName description="HousingUnit Associated View" languagecode="1033" />
    </LocalizedNames>
  </savedquery>
</savedqueries>